{
  "market_summary": {
    "market_phase": "\ud6a1\ubcf4",
    "overall_sentiment": "\ubd80\uc815",
    "short_term_sentiment": "\ub9e4\ub3c4",
    "volume_trend": "\uac10\uc18c",
    "key_levels": {
      "support": [
        92000,
        90000
      ],
      "resistance": [
        95000,
        97000
      ]
    },
    "confidence": 65
  },
  "trading_strategy": {
    "position": "\ub9e4\ub3c4",
    "entry_points": [
      93500,
      94000
    ],
    "stop_loss": 95500,
    "take_profits": [
      91500,
      90500
    ],
    "risk_reward_ratio": 2,
    "recommended_leverage": 5,
    "position_size": "15%",
    "key_risks": [
      "\uace0\ubcc0\ub3d9\uc131",
      "\uae09\uaca9\ud55c \ucd94\uc138\ubcc0\ud654"
    ]
  },
  "analysis_details": {
    "technical_signals": [
      "MACD \ud558\ub77d",
      "RSI \uc911\ub9bd"
    ],
    "market_drivers": [
      "\ubbf8\uccb4\uacb0\uc57d\uc815 \uc218",
      "\ub9e4\uc218/\ub9e4\ub3c4 \ube44\uc728"
    ],
    "key_events": [
      "\ubbf8\uad6d \uc2e4\uc5c5\ub960 \ubc1c\ud45c",
      "\ube44\ud2b8\ucf54\uc778 \ub9c8\uc774\ub2dd \uc5c5\ub370\uc774\ud2b8"
    ]
  },
  "technical_analysis": {
    "trend": "\ud6a1\ubcf4",
    "strength": 42.75,
    "indicators": {
      "rsi": 49.86,
      "macd": "\ud558\ub77d",
      "bollinger": "\uc911\ub9bd",
      "volatility": 188.1
    }
  },
  "market_data": {
    "price_data": {
      "symbol": "BTCUSDT",
      "last_price": 93500.0,
      "price_change_24h": -5.54,
      "volume": 730837.263
    },
    "market_metrics": {
      "funding_rate": -0.00375,
      "next_funding_time": "1737158400000",
      "open_interest": {
        "value": 1029272.355,
        "change_24h": 0.0,
        "timestamp": "1737181800000"
      },
      "long_short_ratio": 1.0
    },
    "order_book": {
      "bids": [
        [
          93409.1,
          0.45
        ],
        [
          93269.3,
          0.001
        ],
        [
          93254.2,
          0.001
        ],
        [
          93173.2,
          0.001
        ],
        [
          93169.2,
          0.002
        ],
        [
          93155.6,
          0.001
        ],
        [
          93130.7,
          0.001
        ],
        [
          93113.2,
          0.176
        ],
        [
          93096.9,
          0.001
        ],
        [
          93000.0,
          0.009
        ],
        [
          92935.6,
          0.001
        ],
        [
          92692.3,
          0.001
        ],
        [
          92558.2,
          0.003
        ],
        [
          92557.4,
          0.002
        ],
        [
          92500.0,
          0.009
        ],
        [
          92390.7,
          0.001
        ],
        [
          92363.7,
          0.45
        ],
        [
          92301.0,
          0.001
        ],
        [
          92210.3,
          0.001
        ],
        [
          92200.0,
          0.001
        ],
        [
          92144.1,
          0.001
        ],
        [
          92000.0,
          0.011
        ],
        [
          91962.7,
          0.001
        ],
        [
          91780.4,
          0.003
        ],
        [
          91714.2,
          0.001
        ]
      ],
      "asks": [
        [
          93454.8,
          0.001
        ],
        [
          93464.8,
          92.743
        ],
        [
          93497.9,
          0.001
        ],
        [
          93533.2,
          3.858
        ],
        [
          93786.4,
          3.281
        ],
        [
          93959.7,
          0.002
        ],
        [
          94000.0,
          0.009
        ],
        [
          94500.0,
          0.009
        ],
        [
          94722.5,
          0.002
        ],
        [
          94864.9,
          0.001
        ],
        [
          94870.2,
          0.001
        ],
        [
          95000.0,
          0.009
        ],
        [
          95026.5,
          0.001
        ],
        [
          95103.8,
          0.001
        ],
        [
          95269.4,
          1190.0
        ],
        [
          95320.7,
          993.831
        ],
        [
          95500.0,
          0.459
        ],
        [
          95634.9,
          0.001
        ],
        [
          95669.4,
          0.003
        ],
        [
          95719.6,
          0.001
        ],
        [
          95756.9,
          0.001
        ],
        [
          95839.8,
          0.001
        ],
        [
          95905.1,
          0.001
        ],
        [
          95978.2,
          0.176
        ],
        [
          96000.0,
          0.009
        ]
      ],
      "bid_volume": 1.1300000000000001,
      "ask_volume": 2284.402
    }
  },
  "timeframe": "15m",
  "timestamp": 1737181828865,
  "saved_at": "2025-01-18 15:30:28 KST"
}