{
  "market_summary": {
    "market_phase": "\ud6a1\ubcf4",
    "overall_sentiment": "\uc911\ub9bd",
    "short_term_sentiment": "\uc911\ub9bd",
    "volume_trend": "\uac10\uc18c",
    "key_levels": {
      "support": [
        55000,
        56000
      ],
      "resistance": [
        59000,
        60000
      ]
    },
    "confidence": 70
  },
  "trading_strategy": {
    "position": "\uad00\ub9dd",
    "entry_points": [],
    "stop_loss": 1,
    "take_profits": [],
    "risk_reward_ratio": 0,
    "recommended_leverage": 1,
    "position_size": "0%",
    "key_risks": [
      "\ubcc0\ub3d9\uc131 \ubd80\uc871"
    ]
  },
  "analysis_details": {
    "technical_signals": [
      "MACD \uc0c1\uc2b9"
    ],
    "market_drivers": [
      "\ud6a1\ubcf4 \ucd94\uc138",
      "RSI \uc911\ub9bd"
    ],
    "key_events": []
  },
  "technical_analysis": {
    "trend": "\ud6a1\ubcf4",
    "strength": 100.0,
    "indicators": {
      "rsi": 50.52,
      "macd": "\uc0c1\uc2b9",
      "bollinger": "\uc911\ub9bd",
      "volatility": 189.76
    }
  },
  "market_data": {
    "price_data": {
      "symbol": "BTCUSDT",
      "last_price": 58110.2,
      "price_change_24h": -19.61,
      "volume": 245245.481
    },
    "market_metrics": {
      "funding_rate": -0.00375,
      "next_funding_time": "1738800000000",
      "open_interest": {
        "value": 868776.041,
        "change_24h": 0.0,
        "timestamp": "1738824300000"
      },
      "long_short_ratio": 1.0
    },
    "order_book": {
      "bids": [
        [
          58100.0,
          0.002
        ],
        [
          58084.8,
          0.001
        ],
        [
          58064.8,
          0.004
        ],
        [
          58056.3,
          0.002
        ],
        [
          58039.9,
          0.443
        ],
        [
          58024.3,
          0.05
        ],
        [
          58000.0,
          0.022
        ],
        [
          57999.8,
          0.001
        ],
        [
          57998.4,
          0.002
        ],
        [
          57937.3,
          0.001
        ],
        [
          57916.0,
          0.002
        ],
        [
          57902.2,
          0.004
        ],
        [
          57814.9,
          0.281
        ],
        [
          57800.0,
          0.002
        ],
        [
          57784.6,
          0.001
        ],
        [
          57739.6,
          0.004
        ],
        [
          57720.0,
          0.013
        ],
        [
          57686.1,
          0.001
        ],
        [
          57631.4,
          0.001
        ],
        [
          57631.3,
          0.05
        ],
        [
          57625.7,
          0.002
        ],
        [
          57577.1,
          0.004
        ],
        [
          57520.4,
          0.003
        ],
        [
          57519.6,
          0.001
        ],
        [
          57500.0,
          0.002
        ]
      ],
      "asks": [
        [
          58110.2,
          76.058
        ],
        [
          58115.7,
          0.002
        ],
        [
          58116.7,
          0.002
        ],
        [
          58156.8,
          0.002
        ],
        [
          58180.1,
          0.002
        ],
        [
          58203.4,
          0.002
        ],
        [
          58226.7,
          0.002
        ],
        [
          58250.0,
          0.002
        ],
        [
          58354.2,
          0.001
        ],
        [
          58358.3,
          0.003
        ],
        [
          58389.9,
          0.004
        ],
        [
          58552.5,
          0.004
        ],
        [
          58595.3,
          0.001
        ],
        [
          58599.8,
          0.001
        ],
        [
          58600.0,
          0.001
        ],
        [
          58772.6,
          0.001
        ],
        [
          58810.1,
          0.05
        ],
        [
          58877.1,
          0.002
        ],
        [
          58900.0,
          0.001
        ],
        [
          58908.2,
          0.001
        ],
        [
          58964.5,
          0.001
        ],
        [
          58969.8,
          0.001
        ],
        [
          58970.1,
          0.001
        ],
        [
          58978.9,
          0.002
        ],
        [
          58991.6,
          0.001
        ]
      ],
      "bid_volume": 0.899,
      "ask_volume": 76.14800000000001
    }
  },
  "timeframe": "15m",
  "timestamp": 1738824312395,
  "saved_at": "2025-02-06 15:45:12 KST"
}